alike/__init__.py
alike-0.1.0.dist-info/LICENSE
alike-0.1.0.dist-info/WHEEL
alike-0.1.0.dist-info/METADATA
alike-0.1.0.dist-info/RECORD
