Metadata-Version: 2.1
Name: alike
Version: 0.1.0
Summary: Loose object comparison for python
License: MIT
Author: Davis Kirkendall
Author-email: davis.e.kirkendall@gmail.com
Requires-Python: >=3.8,<4.0
Classifier: License :: OSI Approved :: MIT License
Classifier: Programming Language :: Python :: 3
Classifier: Programming Language :: Python :: 3.8
Classifier: Programming Language :: Python :: 3.9
